dash_react_flow/DashReactFlow.py
dash_react_flow/DashReactFlowDagre.py
dash_react_flow/__init__.py
dash_react_flow/_imports_.py
dash_react_flow/dash_react_flow.min.js
dash_react_flow/dash_react_flow.min.js.map
dash_react_flow/metadata.json
dash_react_flow/package-info.json
dash_react_flow-0.0.7.dist-info/LICENSE
dash_react_flow-0.0.7.dist-info/METADATA
dash_react_flow-0.0.7.dist-info/WHEEL
dash_react_flow-0.0.7.dist-info/top_level.txt
dash_react_flow-0.0.7.dist-info/RECORD
