Metadata-Version: 2.1
Name: dash-react-flow
Version: 0.0.7
Summary: Project Description
Author: Fevry remy <fevryremy@gmail.com>
License: MIT
Platform: UNKNOWN
Classifier: Framework :: Dash
License-File: LICENSE
